{
    "uid": "165f5242-12ad-4cc9-8bce-0f6484cd83a2",
    "name": "1_DecisionTree",
    "preprocessing": [
        {
            "ml_task": "binary_classification",
            "params": {
                "columns_preprocessing": {},
                "target_preprocessing": [
                    "na_exclude"
                ],
                "ml_task": "binary_classification"
            }
        },
        {
            "ml_task": "binary_classification",
            "params": {
                "columns_preprocessing": {},
                "target_preprocessing": [
                    "na_exclude"
                ],
                "ml_task": "binary_classification"
            }
        },
        {
            "ml_task": "binary_classification",
            "params": {
                "columns_preprocessing": {},
                "target_preprocessing": [
                    "na_exclude"
                ],
                "ml_task": "binary_classification"
            }
        },
        {
            "ml_task": "binary_classification",
            "params": {
                "columns_preprocessing": {},
                "target_preprocessing": [
                    "na_exclude"
                ],
                "ml_task": "binary_classification"
            }
        },
        {
            "ml_task": "binary_classification",
            "params": {
                "columns_preprocessing": {},
                "target_preprocessing": [
                    "na_exclude"
                ],
                "ml_task": "binary_classification"
            }
        }
    ],
    "learners": [
        {
            "library_version": "0.24.1",
            "algorithm_name": "Decision Tree",
            "algorithm_short_name": "Decision Tree",
            "uid": "1a151efb-f4de-4275-9597-71db43828492",
            "params": {
                "model_type": "Decision Tree",
                "ml_task": "binary_classification",
                "n_jobs": -1,
                "seed": 1235,
                "criterion": "gini",
                "max_depth": 3,
                "explain_level": 0
            },
            "name": "learner_fold_0"
        },
        {
            "library_version": "0.24.1",
            "algorithm_name": "Decision Tree",
            "algorithm_short_name": "Decision Tree",
            "uid": "4cb91a23-1648-405f-b7d7-30d7b5c3519d",
            "params": {
                "model_type": "Decision Tree",
                "ml_task": "binary_classification",
                "n_jobs": -1,
                "seed": 1235,
                "criterion": "gini",
                "max_depth": 3,
                "explain_level": 0
            },
            "name": "learner_fold_1"
        },
        {
            "library_version": "0.24.1",
            "algorithm_name": "Decision Tree",
            "algorithm_short_name": "Decision Tree",
            "uid": "5ae98925-dfb1-493f-8d82-dbd43bfc66a7",
            "params": {
                "model_type": "Decision Tree",
                "ml_task": "binary_classification",
                "n_jobs": -1,
                "seed": 1235,
                "criterion": "gini",
                "max_depth": 3,
                "explain_level": 0
            },
            "name": "learner_fold_2"
        },
        {
            "library_version": "0.24.1",
            "algorithm_name": "Decision Tree",
            "algorithm_short_name": "Decision Tree",
            "uid": "977bd0a7-3855-4a5f-b515-bbdf836457a8",
            "params": {
                "model_type": "Decision Tree",
                "ml_task": "binary_classification",
                "n_jobs": -1,
                "seed": 1235,
                "criterion": "gini",
                "max_depth": 3,
                "explain_level": 0
            },
            "name": "learner_fold_3"
        },
        {
            "library_version": "0.24.1",
            "algorithm_name": "Decision Tree",
            "algorithm_short_name": "Decision Tree",
            "uid": "b89e63c2-1609-40cb-a327-3b8306418940",
            "params": {
                "model_type": "Decision Tree",
                "ml_task": "binary_classification",
                "n_jobs": -1,
                "seed": 1235,
                "criterion": "gini",
                "max_depth": 3,
                "explain_level": 0
            },
            "name": "learner_fold_4"
        }
    ],
    "params": {
        "additional": {
            "trees_in_step": 1,
            "train_cant_improve_limit": 0,
            "max_steps": 1,
            "max_rows_limit": null,
            "max_cols_limit": null
        },
        "preprocessing": {
            "columns_preprocessing": {},
            "target_preprocessing": [
                "na_exclude"
            ],
            "ml_task": "binary_classification"
        },
        "validation_strategy": {
            "validation_type": "kfold",
            "shuffle": true,
            "stratify": true,
            "X_path": "AutoML_3/X.parquet",
            "y_path": "AutoML_3/y.parquet",
            "results_path": "AutoML_3",
            "k_folds": 5
        },
        "learner": {
            "model_type": "Decision Tree",
            "ml_task": "binary_classification",
            "n_jobs": -1,
            "seed": 1235,
            "criterion": "gini",
            "max_depth": 3,
            "explain_level": 0
        },
        "ml_task": "binary_classification",
        "explain_level": 0,
        "name": "1_DecisionTree",
        "status": "initialized",
        "final_loss": null,
        "train_time": null,
        "max_time_for_learner": 60
    },
    "saved": [
        "1_DecisionTree/learner_fold_0.decision_tree",
        "1_DecisionTree/learner_fold_1.decision_tree",
        "1_DecisionTree/learner_fold_2.decision_tree",
        "1_DecisionTree/learner_fold_3.decision_tree",
        "1_DecisionTree/learner_fold_4.decision_tree"
    ],
    "predictions_fname": "1_DecisionTree/predictions_out_of_folds.csv",
    "metric_name": "logloss",
    "final_loss": 1.2430951420143934,
    "train_time": 0.6857221126556396,
    "is_stacked": false,
    "threshold": 0.41695776436964116
}