{
    "uid": "6b5cc2e5-5633-47e3-9766-177af44b6215",
    "name": "22_LightGBM",
    "preprocessing": [
        {
            "ml_task": "binary_classification",
            "params": {
                "columns_preprocessing": {},
                "target_preprocessing": [
                    "na_exclude"
                ],
                "ml_task": "binary_classification"
            }
        },
        {
            "ml_task": "binary_classification",
            "params": {
                "columns_preprocessing": {},
                "target_preprocessing": [
                    "na_exclude"
                ],
                "ml_task": "binary_classification"
            }
        },
        {
            "ml_task": "binary_classification",
            "params": {
                "columns_preprocessing": {},
                "target_preprocessing": [
                    "na_exclude"
                ],
                "ml_task": "binary_classification"
            }
        },
        {
            "ml_task": "binary_classification",
            "params": {
                "columns_preprocessing": {},
                "target_preprocessing": [
                    "na_exclude"
                ],
                "ml_task": "binary_classification"
            }
        },
        {
            "ml_task": "binary_classification",
            "params": {
                "columns_preprocessing": {},
                "target_preprocessing": [
                    "na_exclude"
                ],
                "ml_task": "binary_classification"
            }
        },
        {
            "ml_task": "binary_classification",
            "params": {
                "columns_preprocessing": {},
                "target_preprocessing": [
                    "na_exclude"
                ],
                "ml_task": "binary_classification"
            }
        },
        {
            "ml_task": "binary_classification",
            "params": {
                "columns_preprocessing": {},
                "target_preprocessing": [
                    "na_exclude"
                ],
                "ml_task": "binary_classification"
            }
        },
        {
            "ml_task": "binary_classification",
            "params": {
                "columns_preprocessing": {},
                "target_preprocessing": [
                    "na_exclude"
                ],
                "ml_task": "binary_classification"
            }
        },
        {
            "ml_task": "binary_classification",
            "params": {
                "columns_preprocessing": {},
                "target_preprocessing": [
                    "na_exclude"
                ],
                "ml_task": "binary_classification"
            }
        },
        {
            "ml_task": "binary_classification",
            "params": {
                "columns_preprocessing": {},
                "target_preprocessing": [
                    "na_exclude"
                ],
                "ml_task": "binary_classification"
            }
        }
    ],
    "learners": [
        {
            "library_version": "3.0.0",
            "algorithm_name": "LightGBM",
            "algorithm_short_name": "LightGBM",
            "uid": "653fcf3b-4ebf-492c-90d5-3915b7512270",
            "params": {
                "model_type": "LightGBM",
                "ml_task": "binary_classification",
                "n_jobs": -1,
                "seed": 1236,
                "objective": "binary",
                "metric": "binary_logloss",
                "num_leaves": 63,
                "learning_rate": 0.2,
                "feature_fraction": 0.5,
                "bagging_fraction": 1.0,
                "min_data_in_leaf": 10,
                "explain_level": 0
            },
            "name": "learner_fold_0"
        },
        {
            "library_version": "3.0.0",
            "algorithm_name": "LightGBM",
            "algorithm_short_name": "LightGBM",
            "uid": "493ca7b3-5e80-4556-bc8d-71b7956060f2",
            "params": {
                "model_type": "LightGBM",
                "ml_task": "binary_classification",
                "n_jobs": -1,
                "seed": 1236,
                "objective": "binary",
                "metric": "binary_logloss",
                "num_leaves": 63,
                "learning_rate": 0.2,
                "feature_fraction": 0.5,
                "bagging_fraction": 1.0,
                "min_data_in_leaf": 10,
                "explain_level": 0
            },
            "name": "learner_fold_1"
        },
        {
            "library_version": "3.0.0",
            "algorithm_name": "LightGBM",
            "algorithm_short_name": "LightGBM",
            "uid": "95815e8b-9da3-4608-a993-392bfa6618a4",
            "params": {
                "model_type": "LightGBM",
                "ml_task": "binary_classification",
                "n_jobs": -1,
                "seed": 1236,
                "objective": "binary",
                "metric": "binary_logloss",
                "num_leaves": 63,
                "learning_rate": 0.2,
                "feature_fraction": 0.5,
                "bagging_fraction": 1.0,
                "min_data_in_leaf": 10,
                "explain_level": 0
            },
            "name": "learner_fold_2"
        },
        {
            "library_version": "3.0.0",
            "algorithm_name": "LightGBM",
            "algorithm_short_name": "LightGBM",
            "uid": "089c1c84-8156-40b5-86bb-453b81773631",
            "params": {
                "model_type": "LightGBM",
                "ml_task": "binary_classification",
                "n_jobs": -1,
                "seed": 1236,
                "objective": "binary",
                "metric": "binary_logloss",
                "num_leaves": 63,
                "learning_rate": 0.2,
                "feature_fraction": 0.5,
                "bagging_fraction": 1.0,
                "min_data_in_leaf": 10,
                "explain_level": 0
            },
            "name": "learner_fold_3"
        },
        {
            "library_version": "3.0.0",
            "algorithm_name": "LightGBM",
            "algorithm_short_name": "LightGBM",
            "uid": "a8fa05cf-adfc-4b1c-b827-ddd6121ceb1c",
            "params": {
                "model_type": "LightGBM",
                "ml_task": "binary_classification",
                "n_jobs": -1,
                "seed": 1236,
                "objective": "binary",
                "metric": "binary_logloss",
                "num_leaves": 63,
                "learning_rate": 0.2,
                "feature_fraction": 0.5,
                "bagging_fraction": 1.0,
                "min_data_in_leaf": 10,
                "explain_level": 0
            },
            "name": "learner_fold_4"
        },
        {
            "library_version": "3.0.0",
            "algorithm_name": "LightGBM",
            "algorithm_short_name": "LightGBM",
            "uid": "aacc80c5-ece3-4f1a-a5c4-27ef4b8a59f9",
            "params": {
                "model_type": "LightGBM",
                "ml_task": "binary_classification",
                "n_jobs": -1,
                "seed": 1236,
                "objective": "binary",
                "metric": "binary_logloss",
                "num_leaves": 63,
                "learning_rate": 0.2,
                "feature_fraction": 0.5,
                "bagging_fraction": 1.0,
                "min_data_in_leaf": 10,
                "explain_level": 0
            },
            "name": "learner_fold_5"
        },
        {
            "library_version": "3.0.0",
            "algorithm_name": "LightGBM",
            "algorithm_short_name": "LightGBM",
            "uid": "1a0d3971-9edd-4324-b653-442e5636a6fb",
            "params": {
                "model_type": "LightGBM",
                "ml_task": "binary_classification",
                "n_jobs": -1,
                "seed": 1236,
                "objective": "binary",
                "metric": "binary_logloss",
                "num_leaves": 63,
                "learning_rate": 0.2,
                "feature_fraction": 0.5,
                "bagging_fraction": 1.0,
                "min_data_in_leaf": 10,
                "explain_level": 0
            },
            "name": "learner_fold_6"
        },
        {
            "library_version": "3.0.0",
            "algorithm_name": "LightGBM",
            "algorithm_short_name": "LightGBM",
            "uid": "b47f4e2e-27fd-4b2d-8273-33f34a49ec95",
            "params": {
                "model_type": "LightGBM",
                "ml_task": "binary_classification",
                "n_jobs": -1,
                "seed": 1236,
                "objective": "binary",
                "metric": "binary_logloss",
                "num_leaves": 63,
                "learning_rate": 0.2,
                "feature_fraction": 0.5,
                "bagging_fraction": 1.0,
                "min_data_in_leaf": 10,
                "explain_level": 0
            },
            "name": "learner_fold_7"
        },
        {
            "library_version": "3.0.0",
            "algorithm_name": "LightGBM",
            "algorithm_short_name": "LightGBM",
            "uid": "b7e1d525-4504-4372-87ff-d097e8915f1d",
            "params": {
                "model_type": "LightGBM",
                "ml_task": "binary_classification",
                "n_jobs": -1,
                "seed": 1236,
                "objective": "binary",
                "metric": "binary_logloss",
                "num_leaves": 63,
                "learning_rate": 0.2,
                "feature_fraction": 0.5,
                "bagging_fraction": 1.0,
                "min_data_in_leaf": 10,
                "explain_level": 0
            },
            "name": "learner_fold_8"
        },
        {
            "library_version": "3.0.0",
            "algorithm_name": "LightGBM",
            "algorithm_short_name": "LightGBM",
            "uid": "8d85d8a9-30ef-4f52-a328-77f9b4433c0c",
            "params": {
                "model_type": "LightGBM",
                "ml_task": "binary_classification",
                "n_jobs": -1,
                "seed": 1236,
                "objective": "binary",
                "metric": "binary_logloss",
                "num_leaves": 63,
                "learning_rate": 0.2,
                "feature_fraction": 0.5,
                "bagging_fraction": 1.0,
                "min_data_in_leaf": 10,
                "explain_level": 0
            },
            "name": "learner_fold_9"
        }
    ],
    "params": {
        "additional": {
            "max_rounds": 10000,
            "early_stopping_rounds": 50,
            "max_rows_limit": null,
            "max_cols_limit": null
        },
        "preprocessing": {
            "columns_preprocessing": {},
            "target_preprocessing": [
                "na_exclude"
            ],
            "ml_task": "binary_classification"
        },
        "validation_strategy": {
            "validation_type": "kfold",
            "shuffle": true,
            "stratify": true,
            "X_path": "AutoML_5/X.parquet",
            "y_path": "AutoML_5/y.parquet",
            "results_path": "AutoML_5",
            "k_folds": 10
        },
        "learner": {
            "model_type": "LightGBM",
            "ml_task": "binary_classification",
            "n_jobs": -1,
            "seed": 1236,
            "objective": "binary",
            "metric": "binary_logloss",
            "num_leaves": 63,
            "learning_rate": 0.2,
            "feature_fraction": 0.5,
            "bagging_fraction": 1.0,
            "min_data_in_leaf": 10,
            "explain_level": 0
        },
        "ml_task": "binary_classification",
        "explain_level": 0,
        "name": "22_LightGBM",
        "status": "initialized",
        "final_loss": null,
        "train_time": null,
        "max_time_for_learner": 60
    },
    "saved": [
        "22_LightGBM/learner_fold_0.lightgbm",
        "22_LightGBM/learner_fold_1.lightgbm",
        "22_LightGBM/learner_fold_2.lightgbm",
        "22_LightGBM/learner_fold_3.lightgbm",
        "22_LightGBM/learner_fold_4.lightgbm",
        "22_LightGBM/learner_fold_5.lightgbm",
        "22_LightGBM/learner_fold_6.lightgbm",
        "22_LightGBM/learner_fold_7.lightgbm",
        "22_LightGBM/learner_fold_8.lightgbm",
        "22_LightGBM/learner_fold_9.lightgbm"
    ],
    "predictions_fname": "22_LightGBM/predictions_out_of_folds.csv",
    "metric_name": "logloss",
    "final_loss": 0.2901095158063398,
    "train_time": 1.120553970336914,
    "is_stacked": false,
    "threshold": 0.47120704164960303
}