{
    "uid": "cd5ec605-04fe-413d-806b-a11ece7df98b",
    "name": "120_ExtraTrees_SelectedFeatures",
    "preprocessing": [
        {
            "ml_task": "binary_classification",
            "drop_features": [
                "feature_19",
                "feature_10",
                "feature_15",
                "feature_6",
                "feature_2",
                "feature_5",
                "feature_7",
                "feature_17",
                "feature_13",
                "feature_23",
                "feature_22",
                "feature_20",
                "feature_21",
                "feature_24",
                "feature_18",
                "feature_16",
                "feature_14",
                "feature_11"
            ],
            "params": {
                "columns_preprocessing": {},
                "target_preprocessing": [
                    "na_exclude"
                ],
                "ml_task": "binary_classification",
                "drop_features": [
                    "feature_19",
                    "feature_10",
                    "feature_15",
                    "feature_6",
                    "feature_2",
                    "feature_5",
                    "random_feature",
                    "feature_7",
                    "feature_17",
                    "feature_13",
                    "feature_23",
                    "feature_9_ratio_feature_13",
                    "feature_17_ratio_feature_13",
                    "feature_23_sum_feature_13",
                    "feature_13_diff_feature_24",
                    "feature_22",
                    "feature_20",
                    "feature_13_multiply_feature_9",
                    "feature_13_ratio_feature_17",
                    "feature_24_multiply_feature_13",
                    "feature_17_multiply_feature_13",
                    "feature_21",
                    "feature_24_ratio_feature_13",
                    "feature_13_ratio_feature_2",
                    "feature_24",
                    "feature_18",
                    "feature_16",
                    "feature_14",
                    "feature_11"
                ]
            }
        },
        {
            "ml_task": "binary_classification",
            "drop_features": [
                "feature_19",
                "feature_10",
                "feature_15",
                "feature_6",
                "feature_2",
                "feature_5",
                "feature_7",
                "feature_17",
                "feature_13",
                "feature_23",
                "feature_22",
                "feature_20",
                "feature_21",
                "feature_24",
                "feature_18",
                "feature_16",
                "feature_14",
                "feature_11"
            ],
            "params": {
                "columns_preprocessing": {},
                "target_preprocessing": [
                    "na_exclude"
                ],
                "ml_task": "binary_classification",
                "drop_features": [
                    "feature_19",
                    "feature_10",
                    "feature_15",
                    "feature_6",
                    "feature_2",
                    "feature_5",
                    "random_feature",
                    "feature_7",
                    "feature_17",
                    "feature_13",
                    "feature_23",
                    "feature_9_ratio_feature_13",
                    "feature_17_ratio_feature_13",
                    "feature_23_sum_feature_13",
                    "feature_13_diff_feature_24",
                    "feature_22",
                    "feature_20",
                    "feature_13_multiply_feature_9",
                    "feature_13_ratio_feature_17",
                    "feature_24_multiply_feature_13",
                    "feature_17_multiply_feature_13",
                    "feature_21",
                    "feature_24_ratio_feature_13",
                    "feature_13_ratio_feature_2",
                    "feature_24",
                    "feature_18",
                    "feature_16",
                    "feature_14",
                    "feature_11"
                ]
            }
        },
        {
            "ml_task": "binary_classification",
            "drop_features": [
                "feature_19",
                "feature_10",
                "feature_15",
                "feature_6",
                "feature_2",
                "feature_5",
                "feature_7",
                "feature_17",
                "feature_13",
                "feature_23",
                "feature_22",
                "feature_20",
                "feature_21",
                "feature_24",
                "feature_18",
                "feature_16",
                "feature_14",
                "feature_11"
            ],
            "params": {
                "columns_preprocessing": {},
                "target_preprocessing": [
                    "na_exclude"
                ],
                "ml_task": "binary_classification",
                "drop_features": [
                    "feature_19",
                    "feature_10",
                    "feature_15",
                    "feature_6",
                    "feature_2",
                    "feature_5",
                    "random_feature",
                    "feature_7",
                    "feature_17",
                    "feature_13",
                    "feature_23",
                    "feature_9_ratio_feature_13",
                    "feature_17_ratio_feature_13",
                    "feature_23_sum_feature_13",
                    "feature_13_diff_feature_24",
                    "feature_22",
                    "feature_20",
                    "feature_13_multiply_feature_9",
                    "feature_13_ratio_feature_17",
                    "feature_24_multiply_feature_13",
                    "feature_17_multiply_feature_13",
                    "feature_21",
                    "feature_24_ratio_feature_13",
                    "feature_13_ratio_feature_2",
                    "feature_24",
                    "feature_18",
                    "feature_16",
                    "feature_14",
                    "feature_11"
                ]
            }
        },
        {
            "ml_task": "binary_classification",
            "drop_features": [
                "feature_19",
                "feature_10",
                "feature_15",
                "feature_6",
                "feature_2",
                "feature_5",
                "feature_7",
                "feature_17",
                "feature_13",
                "feature_23",
                "feature_22",
                "feature_20",
                "feature_21",
                "feature_24",
                "feature_18",
                "feature_16",
                "feature_14",
                "feature_11"
            ],
            "params": {
                "columns_preprocessing": {},
                "target_preprocessing": [
                    "na_exclude"
                ],
                "ml_task": "binary_classification",
                "drop_features": [
                    "feature_19",
                    "feature_10",
                    "feature_15",
                    "feature_6",
                    "feature_2",
                    "feature_5",
                    "random_feature",
                    "feature_7",
                    "feature_17",
                    "feature_13",
                    "feature_23",
                    "feature_9_ratio_feature_13",
                    "feature_17_ratio_feature_13",
                    "feature_23_sum_feature_13",
                    "feature_13_diff_feature_24",
                    "feature_22",
                    "feature_20",
                    "feature_13_multiply_feature_9",
                    "feature_13_ratio_feature_17",
                    "feature_24_multiply_feature_13",
                    "feature_17_multiply_feature_13",
                    "feature_21",
                    "feature_24_ratio_feature_13",
                    "feature_13_ratio_feature_2",
                    "feature_24",
                    "feature_18",
                    "feature_16",
                    "feature_14",
                    "feature_11"
                ]
            }
        },
        {
            "ml_task": "binary_classification",
            "drop_features": [
                "feature_19",
                "feature_10",
                "feature_15",
                "feature_6",
                "feature_2",
                "feature_5",
                "feature_7",
                "feature_17",
                "feature_13",
                "feature_23",
                "feature_22",
                "feature_20",
                "feature_21",
                "feature_24",
                "feature_18",
                "feature_16",
                "feature_14",
                "feature_11"
            ],
            "params": {
                "columns_preprocessing": {},
                "target_preprocessing": [
                    "na_exclude"
                ],
                "ml_task": "binary_classification",
                "drop_features": [
                    "feature_19",
                    "feature_10",
                    "feature_15",
                    "feature_6",
                    "feature_2",
                    "feature_5",
                    "random_feature",
                    "feature_7",
                    "feature_17",
                    "feature_13",
                    "feature_23",
                    "feature_9_ratio_feature_13",
                    "feature_17_ratio_feature_13",
                    "feature_23_sum_feature_13",
                    "feature_13_diff_feature_24",
                    "feature_22",
                    "feature_20",
                    "feature_13_multiply_feature_9",
                    "feature_13_ratio_feature_17",
                    "feature_24_multiply_feature_13",
                    "feature_17_multiply_feature_13",
                    "feature_21",
                    "feature_24_ratio_feature_13",
                    "feature_13_ratio_feature_2",
                    "feature_24",
                    "feature_18",
                    "feature_16",
                    "feature_14",
                    "feature_11"
                ]
            }
        }
    ],
    "learners": [
        {
            "library_version": "0.24.1",
            "algorithm_name": "Extra Trees Classifier",
            "algorithm_short_name": "Extra Trees",
            "uid": "d34e948b-3334-4869-b0c9-7df512d0d2c4",
            "params": {
                "model_type": "Extra Trees",
                "ml_task": "binary_classification",
                "n_jobs": -1,
                "seed": 1239,
                "criterion": "gini",
                "max_features": 0.9,
                "min_samples_split": 50,
                "max_depth": 3,
                "explain_level": 0
            },
            "name": "learner_fold_0"
        },
        {
            "library_version": "0.24.1",
            "algorithm_name": "Extra Trees Classifier",
            "algorithm_short_name": "Extra Trees",
            "uid": "211dc32b-a321-4afb-8fa7-3926f2837528",
            "params": {
                "model_type": "Extra Trees",
                "ml_task": "binary_classification",
                "n_jobs": -1,
                "seed": 1239,
                "criterion": "gini",
                "max_features": 0.9,
                "min_samples_split": 50,
                "max_depth": 3,
                "explain_level": 0
            },
            "name": "learner_fold_1"
        },
        {
            "library_version": "0.24.1",
            "algorithm_name": "Extra Trees Classifier",
            "algorithm_short_name": "Extra Trees",
            "uid": "276153bd-488e-4f4e-80b6-2035d7c41842",
            "params": {
                "model_type": "Extra Trees",
                "ml_task": "binary_classification",
                "n_jobs": -1,
                "seed": 1239,
                "criterion": "gini",
                "max_features": 0.9,
                "min_samples_split": 50,
                "max_depth": 3,
                "explain_level": 0
            },
            "name": "learner_fold_2"
        },
        {
            "library_version": "0.24.1",
            "algorithm_name": "Extra Trees Classifier",
            "algorithm_short_name": "Extra Trees",
            "uid": "ee80c05c-30e8-4414-b0e3-4bbc24c08876",
            "params": {
                "model_type": "Extra Trees",
                "ml_task": "binary_classification",
                "n_jobs": -1,
                "seed": 1239,
                "criterion": "gini",
                "max_features": 0.9,
                "min_samples_split": 50,
                "max_depth": 3,
                "explain_level": 0
            },
            "name": "learner_fold_3"
        },
        {
            "library_version": "0.24.1",
            "algorithm_name": "Extra Trees Classifier",
            "algorithm_short_name": "Extra Trees",
            "uid": "f65044bd-2ef3-41cb-b54e-41ba245710c7",
            "params": {
                "model_type": "Extra Trees",
                "ml_task": "binary_classification",
                "n_jobs": -1,
                "seed": 1239,
                "criterion": "gini",
                "max_features": 0.9,
                "min_samples_split": 50,
                "max_depth": 3,
                "explain_level": 0
            },
            "name": "learner_fold_4"
        }
    ],
    "params": {
        "additional": {
            "trees_in_step": 100,
            "max_steps": 50,
            "early_stopping_rounds": 50,
            "max_rows_limit": null,
            "max_cols_limit": null
        },
        "preprocessing": {
            "columns_preprocessing": {},
            "target_preprocessing": [
                "na_exclude"
            ],
            "ml_task": "binary_classification",
            "drop_features": [
                "feature_19",
                "feature_10",
                "feature_15",
                "feature_6",
                "feature_2",
                "feature_5",
                "random_feature",
                "feature_7",
                "feature_17",
                "feature_13",
                "feature_23",
                "feature_9_ratio_feature_13",
                "feature_17_ratio_feature_13",
                "feature_23_sum_feature_13",
                "feature_13_diff_feature_24",
                "feature_22",
                "feature_20",
                "feature_13_multiply_feature_9",
                "feature_13_ratio_feature_17",
                "feature_24_multiply_feature_13",
                "feature_17_multiply_feature_13",
                "feature_21",
                "feature_24_ratio_feature_13",
                "feature_13_ratio_feature_2",
                "feature_24",
                "feature_18",
                "feature_16",
                "feature_14",
                "feature_11"
            ]
        },
        "validation_strategy": {
            "validation_type": "kfold",
            "shuffle": true,
            "stratify": true,
            "X_path": "AutoML_1/X.parquet",
            "y_path": "AutoML_1/y.parquet",
            "results_path": "AutoML_1",
            "k_folds": 5
        },
        "learner": {
            "model_type": "Extra Trees",
            "ml_task": "binary_classification",
            "n_jobs": -1,
            "seed": 1239,
            "criterion": "gini",
            "max_features": 0.9,
            "min_samples_split": 50,
            "max_depth": 3,
            "explain_level": 0
        },
        "ml_task": "binary_classification",
        "explain_level": 0,
        "name": "120_ExtraTrees_SelectedFeatures",
        "status": "initialized",
        "final_loss": null,
        "train_time": null,
        "max_time_for_learner": 60
    },
    "saved": [
        "120_ExtraTrees_SelectedFeatures/learner_fold_0.extra_trees",
        "120_ExtraTrees_SelectedFeatures/learner_fold_1.extra_trees",
        "120_ExtraTrees_SelectedFeatures/learner_fold_2.extra_trees",
        "120_ExtraTrees_SelectedFeatures/learner_fold_3.extra_trees",
        "120_ExtraTrees_SelectedFeatures/learner_fold_4.extra_trees"
    ],
    "predictions_fname": "120_ExtraTrees_SelectedFeatures/predictions_out_of_folds.csv",
    "metric_name": "logloss",
    "final_loss": 0.6293754773418276,
    "train_time": 3.4541358947753906,
    "is_stacked": false,
    "threshold": 0.4081095680382386
}